loaden/__init__.py
loaden/cli.py
loaden/config.py
loaden/py.typed
loaden-0.1.0.dist-info/METADATA
loaden-0.1.0.dist-info/WHEEL
loaden-0.1.0.dist-info/entry_points.txt
loaden-0.1.0.dist-info/licenses/LICENSE
loaden-0.1.0.dist-info/RECORD
