Metadata-Version: 2.4
Name: loaden
Version: 0.1.0
Summary: YAML config loader with file includes, ${VAR} substitution, .env support, and deep merging
Project-URL: Homepage, https://github.com/mattjoyce/loaden
Project-URL: Repository, https://github.com/mattjoyce/loaden
Project-URL: Issues, https://github.com/mattjoyce/loaden/issues
Author-email: Matt Joyce <matt.joyce@gmail.com>
License: GPL-3.0-or-later
License-File: LICENSE
Keywords: config,configuration,environment,settings,yaml
Classifier: Development Status :: 4 - Beta
Classifier: Intended Audience :: Developers
Classifier: License :: OSI Approved :: GNU General Public License v3 (GPLv3)
Classifier: Programming Language :: Python :: 3
Classifier: Programming Language :: Python :: 3.10
Classifier: Programming Language :: Python :: 3.11
Classifier: Programming Language :: Python :: 3.12
Classifier: Programming Language :: Python :: 3.13
Classifier: Topic :: Software Development :: Libraries :: Python Modules
Requires-Python: >=3.10
Requires-Dist: pyyaml>=6.0
Provides-Extra: dev
Requires-Dist: mypy; extra == 'dev'
Requires-Dist: pytest; extra == 'dev'
Requires-Dist: ruff; extra == 'dev'
